{
  "id": "007",
  "headline": "Senator Filibuster McStall Spends 14 Hours Reading The Phone Book To Avoid Voting",
  "summary": "He reached the 'W' section before colleagues physically removed him from the podium.",
  "fullBody": "Senator Filibuster McStall delivered a marathon 14-hour speech consisting entirely of the local phone book to delay a vote on mandatory nap breaks. 'Smith, Steven. Smith, Susan. Smith, Thomas...' McStall droned as colleagues dozed off. He was finally dragged from the podium at 3 AM by security after reaching 'Zimmerman, Zachary.' McStall declared the filibuster 'a victory for procrastination everywhere.'",
  "category": "politics",
  "imageUrl": "https://raw.githubusercontent.com/factictionary/news-content/main/images/2026-06-09/007.jpg",
  "publishedAt": "1 day ago",
  "readTimeSeconds": 82,
  "tags": [
    "Politics",
    "Satire",
    "Filibuster"
  ],
  "isBreaking": true,
  "unique_id": "2026-06-09_007",
  "date": "2026-06-09"
}