{
  "id": "036",
  "headline": "Guy's 'I'm Just Being Realistic' Is Code For 'I Will Crush Your Dreams With Statistics'",
  "summary": "'You probably won't succeed,' Jake said. 'Statistically.' His friend stopped sharing goals. Jake is now alone.",
  "fullBody": "Jake Realistic has an opinion on everything: 'that probably won't work.' His friend shared a dream. 'Statistically, you'll fail,' Jake said. His friend stopped talking. 'I'm just being honest,' Jake said. He is now alone. 'People can't handle the truth,' Jake said. His therapist suggested 'maybe supporting people.' 'I'm supporting them with data,' Jake said. The data shows he has no friends.",
  "category": "relationships",
  "imageUrl": "https://raw.githubusercontent.com/factictionary/news-content/main/images/2026-06-16/036.jpg",
  "publishedAt": "4 days ago",
  "readTimeSeconds": 66,
  "tags": [
    "Negativity",
    "Relationships",
    "Satire"
  ],
  "isBreaking": false,
  "unique_id": "2026-06-16_036",
  "date": "2026-06-16"
}