{
  "id": "013",
  "headline": "Parrot Learns To Order Pizza Online, Now Has A Delivery History Longer Than Owner",
  "summary": "The parrot orders pizza every Tuesday at 6 PM. The delivery driver knows him by name.",
  "fullBody": "Polly the parrot has learned to order pizza online using his owner's phone. 'He orders a large pepperoni every Tuesday,' his owner said. 'I don't even like pepperoni.' The delivery driver knows Polly by name. 'It's always the parrot,' the driver said. Polly has started tipping generously. 'He has a system,' the owner said. Polly now has a frequent pizza rewards card. 'I'm impressed,' the owner said.",
  "category": "pets",
  "imageUrl": "https://raw.githubusercontent.com/factictionary/news-content/main/images/2026-06-18/013.jpg",
  "publishedAt": "1 day ago",
  "readTimeSeconds": 66,
  "tags": [
    "Pets",
    "Food",
    "Satire"
  ],
  "isBreaking": false,
  "unique_id": "2026-06-18_013",
  "date": "2026-06-18"
}