{
  "id": "049",
  "headline": "President Leotard DiCapriCat signs order",
  "summary": "Sources say the janitor quit in protest",
  "fullBody": "According to leaked documents President Leotard DiCapriCat signs order Strangely enough, Twitter/X imploded We will continue to monitor this story.",
  "category": "politics",
  "imageUrl": "https://raw.githubusercontent.com/factictionary/news-content/main/images/2026-06-05/049.jpg",
  "publishedAt": "14 hrs ago",
  "readTimeSeconds": 74,
  "tags": [
    "Politics"
  ],
  "isBreaking": false,
  "unique_id": "2026-06-05_049",
  "date": "2026-06-05"
}