{
  "id": "021",
  "headline": "Woman's 'I'm Not Like Other Girls' Phase Is Documented In A Cringe Binder She Keeps Under Her Bed",
  "summary": "The binder includes her 'cool girl' manifesto and a list of 'approved interests.' She's now in therapy.",
  "fullBody": "Amanda NotLikeOtherGirls has a binder from her 'pick me' era. 'I only liked obscure bands and hating things,' Amanda read aloud. 'Why did I write this?' The binder includes a 'cool girl oath' and a list of 'acceptable hobbies' (skateboarding, not reading). Her therapist has the binder now. 'We're processing,' Amanda said. She's now 'exactly like other girls' and 'happier than ever.' The binder has been burned. 'Goodbye, cringe,' she said.",
  "category": "personal growth",
  "imageUrl": "https://raw.githubusercontent.com/factictionary/news-content/main/images/2026-06-16/021.jpg",
  "publishedAt": "2 days ago",
  "readTimeSeconds": 68,
  "tags": [
    "Cringe",
    "Growth",
    "Satire"
  ],
  "isBreaking": false,
  "unique_id": "2026-06-16_021",
  "date": "2026-06-16"
}