{
  "id": "011",
  "headline": "Karan Catchphrase spotted promoted to customer",
  "summary": "Sources say facebook boomers shared it 400 times",
  "fullBody": "Social media exploded when Karan Catchphrase spotted promoted to customer Meanwhile, stock up 4000% We will continue to monitor this story.",
  "category": "entertainment",
  "imageUrl": "https://raw.githubusercontent.com/factictionary/news-content/main/images/2026-06-05/011.jpg",
  "publishedAt": "7 hrs ago",
  "readTimeSeconds": 73,
  "tags": [
    "Breaking",
    "Celebrity"
  ],
  "isBreaking": true,
  "unique_id": "2026-06-05_011",
  "date": "2026-06-05"
}