{
  "id": "002",
  "headline": "Florida man marries half-cat half-toaster",
  "summary": "Sources say a single tweet went viral",
  "fullBody": "According to leaked documents Florida man marries half-cat half-toaster Adding to the confusion, spokesperson blamed childhood trauma The internet has already moved on.",
  "category": "weird",
  "imageUrl": "https://raw.githubusercontent.com/factictionary/news-content/main/images/2026-06-05/002.jpg",
  "publishedAt": "14 hrs ago",
  "readTimeSeconds": 55,
  "tags": [
    "Breaking",
    "Weird"
  ],
  "isBreaking": true,
  "unique_id": "2026-06-05_002",
  "date": "2026-06-05"
}