{
  "id": "035",
  "headline": "Cows Unionize and Demand 4-Day Work Week of Grazing",
  "summary": "Moo-vement spreads across dairy farms worldwide.",
  "fullBody": "Bessie the spokesperson cow led negotiations for better hay benefits and mental health days. Farmers are struggling to meet demands as the herd refuses to produce milk until terms are met. Cheese prices expected to skyrocket.",
  "category": "animals",
  "imageUrl": "https://raw.githubusercontent.com/factictionary/news-content/main/images/2026-06-22/035.jpg",
  "publishedAt": "5 days ago",
  "readTimeSeconds": 77,
  "tags": [
    "Cows",
    "Labor",
    "Farming"
  ],
  "isBreaking": false,
  "unique_id": "2026-06-22_035",
  "date": "2026-06-22"
}