{
  "id": "033",
  "headline": "Man Who Has Never Read Terms And Conditions Finds He Technically Owes His Soul To Abodey",
  "summary": "Legal review confirms this is valid. Abodey has not yet exercised the clause but 'reserves the right to.'",
  "fullBody": "Coimbatore graphic designer Suresh Rajan, 29, made the troubling discovery last week that a clause buried in section 41.7.b of the Abodey Creative Cloud terms he agreed to in 2018 technically entitles Abodey Systems Inc. to ownership of 'any and all intangible assets including, but not limited to, creative energy, spiritual residue, and applicable soul-adjacent intellectual property generated during periods of active licence.' A legal review commissioned by Suresh and his deeply concerned mother confirmed the clause is 'technically valid under current IP law in three jurisdictions.' Abodey's spokesperson said the company 'has no immediate plans to exercise this provision' but noted the terms are 'reviewed annually.' Suresh has downgraded to the Photography Plan.",
  "category": "tech",
  "imageUrl": "https://raw.githubusercontent.com/factictionary/news-content/main/images/2026-06-06/033.jpg",
  "imagePrompt": "A man looking horrified reading Abodey terms and conditions, soul floating out of him toward Abodey logo, comic editorial illustration, flat bold design, dark humor tone",
  "publishedAt": "3 days ago",
  "readTimeSeconds": 68,
  "tags": [
    "Adobe",
    "Tech",
    "Legal",
    "Satire"
  ],
  "isBreaking": false,
  "unique_id": "2026-06-06_033",
  "date": "2026-06-06"
}