{
  "id": "024",
  "headline": "Senator Bluster McWindbag Proposes Law Making It Illegal To Say 'Actually'",
  "summary": "The bill exempts senators because they 'need it for technical corrections.'",
  "fullBody": "Senator Bluster McWindbag has proposed a law making the word 'actually' illegal in casual conversation. 'Actually, people use it to sound smarter than they are,' McWindbag said, using the word himself. The bill exempts senators, professors, and anyone currently being corrected. Critics call it 'hypocritical' and 'actually quite silly.' McWindbag responded, 'Actually, your criticism is noted but ignored.' The bill is expected to pass because no one can agree on how to argue against it.",
  "category": "politics",
  "imageUrl": "https://raw.githubusercontent.com/factictionary/news-content/main/images/2026-06-09/024.jpg",
  "publishedAt": "1 day ago",
  "readTimeSeconds": 74,
  "tags": [
    "Politics",
    "Satire",
    "Legal"
  ],
  "isBreaking": false,
  "unique_id": "2026-06-09_024",
  "date": "2026-06-09"
}