{
  "id": "005",
  "headline": "Flat Earthers Pivot: Earth Is Actually A Square, Corners Located In Canada, Australia, Siberia, And Pune",
  "summary": "The society demands a formal apology from the 'globalist sphere lobby' and new maps by July.",
  "fullBody": "The Global Flat Earth Society held its annual convention in Goa this week, ending with a historic unanimous resolution formally abandoning the flat Earth theory in favour of the Square Earth theory. According to the new model, the Earth is a perfect square with corners located in northern Canada, eastern Australia, central Siberia, and — for reasons the society's chief cartographer described as 'geometrically inevitable' — Pune, Maharashtra. The society issued a press release demanding a formal apology from what it called 'the globalist sphere lobby,' new school maps, and a redesign of all airline route maps before July 15th. The Pune Municipal Corporation has not yet commented.",
  "category": "weird",
  "imageUrl": "https://raw.githubusercontent.com/factictionary/news-content/main/images/2026-06-06/005.jpg",
  "imagePrompt": "A square planet earth floating in space with four sharp corners, comic flat design illustration, bold outlines, space background",
  "publishedAt": "5 hrs ago",
  "readTimeSeconds": 65,
  "tags": [
    "Weird",
    "Science",
    "Conspiracy",
    "Geography"
  ],
  "isBreaking": false,
  "unique_id": "2026-06-06_005",
  "date": "2026-06-06"
}