{
  "id": "010",
  "headline": "Man Goes Viral For Wearing The Same Suit To Every Meeting For 7 Years, Nobody Noticed",
  "summary": "The suit has become legendary. His coworkers have started a fan club. 'It's the same suit?' they asked.",
  "fullBody": "Jake has worn the same suit to every business meeting for 7 years. Nobody noticed. 'I have 5 identical suits,' Jake said. 'But they're basically the same.' His coworkers were shocked. 'I thought it was a different suit every time,' one said. 'It was the same suit,' Jake said. The suit has been named 'Suit McSuitface' and has its own Instagram. Jake is now a fashion icon. 'I'm not a fashion person,' Jake said. 'I'm just consistent.'",
  "category": "human behavior",
  "imageUrl": "https://raw.githubusercontent.com/factictionary/news-content/main/images/2026-06-18/010.jpg",
  "publishedAt": "20 hrs ago",
  "readTimeSeconds": 66,
  "tags": [
    "Fashion",
    "Work",
    "Satire"
  ],
  "isBreaking": false,
  "unique_id": "2026-06-18_010",
  "date": "2026-06-18"
}