{
  "id": "010",
  "headline": "Snaccify launches a vacuum with self-esteem issues",
  "summary": "Sources say stock up 4000%",
  "fullBody": "In a shocking development Snaccify launches a vacuum with self-esteem issues However, TikTok cried The internet has already moved on.",
  "category": "tech",
  "imageUrl": "https://raw.githubusercontent.com/factictionary/news-content/main/images/2026-06-05/010.jpg",
  "publishedAt": "20 hrs ago",
  "readTimeSeconds": 106,
  "tags": [
    "Tech"
  ],
  "isBreaking": false,
  "unique_id": "2026-06-05_010",
  "date": "2026-06-05"
}