{
  "id": "022",
  "headline": "Woman's 'Dry January' Lasted 47 Minutes, Then She Posted 'Hydrated February' As A Compromise",
  "summary": "Hydrated February involves wine with 'a lot of ice for hydration purposes.'",
  "fullBody": "Amanda Resolution posted her Dry January commitment and broke it 47 minutes later. 'It's about balance,' Amanda explained, sipping wine. She has now coined 'Hydrated February' — which involves drinking 'water-adjacent beverages' like 'wine with ice' and 'vodka with a splash of hydration.' Her friends have started a betting pool. Amanda is currently 'manifesting moderation' with a margarita. 'It has lime,' she said. 'That's a fruit. That's healthy.'",
  "category": "funny",
  "imageUrl": "https://raw.githubusercontent.com/factictionary/news-content/main/images/2026-06-14/022.jpg",
  "publishedAt": "2 days ago",
  "readTimeSeconds": 62,
  "tags": [
    "New Year",
    "Comedy",
    "Alcohol"
  ],
  "isBreaking": false,
  "unique_id": "2026-06-14_022",
  "date": "2026-06-14"
}