{
  "id": "095",
  "headline": "New Hair Salon Offers 'Brutally Honest Mirror' That Comments On Your Hair Choices",
  "summary": "The 'Truth Mirror' says things like 'Are you sure about this cut? I'm asking for science.'",
  "fullBody": "The Brutal Beauty salon has installed a 'Truth Mirror' in every styling station that provides unfiltered commentary on customers' hair decisions. The mirror uses AI to analyze cuts and colors and delivers honest feedback like 'This color makes you look like you're going through a phase' and 'That cut is fine, but you could do better, we've both seen your previous styles.' One customer said, 'I showed the mirror a photo of a style I wanted and it said -That's a lot of commitment for something that will look bad in 3 weeks, but you do you. I cried, but my hair does look better now.' The salon reports a 47% increase in customers who 'want someone to tell them the truth about their hair.' The mirror also offers complimentary insults about outfit choices.",
  "category": "lifestyle",
  "imageUrl": "https://raw.githubusercontent.com/factictionary/news-content/main/images/2026-06-08/095.jpg",
  "imagePrompt": "Person in salon chair looking in mirror that has angry face and speech bubble saying THAT'S A CHOICE, stylist in background shrugging, comic illustration, flat design, pink and gray colors",
  "publishedAt": "6 days ago",
  "readTimeSeconds": 78,
  "tags": [
    "Lifestyle",
    "Salon",
    "Mirror",
    "Satire"
  ],
  "isBreaking": false,
  "unique_id": "2026-06-08_095",
  "date": "2026-06-08"
}